GAPlanetS/AutomateKLIP.py
GAPlanetS/GhostIsolation.py
GAPlanetS/MasterKLIP.sh
GAPlanetS/SNRMap_new.py
GAPlanetS/SliceCube_new.py
GAPlanetS/__init__.py
GAPlanetS/gaplanets.py
GAPlanetS/paramexplorer.py
GAPlanetS/preprocess.py
GAPlanetS/test_pe.py
GAPlanetS-0.1.0.dist-info/METADATA
GAPlanetS-0.1.0.dist-info/WHEEL
GAPlanetS-0.1.0.dist-info/top_level.txt
GAPlanetS-0.1.0.dist-info/RECORD
